xingpyc/__init__.py
xingpyc/example.py
xingpyc-0.4.14.dist-info/METADATA
xingpyc-0.4.14.dist-info/WHEEL
xingpyc-0.4.14.dist-info/top_level.txt
xingpyc-0.4.14.dist-info/RECORD
