Metadata-Version: 2.1
Name: xingpyc
Version: 0.4.14
Summary: Official Xing Python API
Author-email: 燃棘 <xxx@xxx.com>
Project-URL: Homepage, https://github.com/Lx017/XingPyClient
Project-URL: Issues, https://github.com/Lx017/XingPyClient/issues
Classifier: Programming Language :: Python :: 3
Classifier: License :: OSI Approved :: MIT License
Classifier: Operating System :: OS Independent
Requires-Python: >=3.8
Requires-Dist: websocket-client >=1.8.0
Requires-Dist: websockets >=12.0
Requires-Dist: numpy >=1.18.0
Requires-Dist: pillow
Requires-Dist: aiortc >=1.8.0
Requires-Dist: mss
